groper.py
groper-0.4.1.dist-info/METADATA
groper-0.4.1.dist-info/WHEEL
groper-0.4.1.dist-info/licenses/LICENSE.txt
groper-0.4.1.dist-info/RECORD
