Metadata-Version: 2.3
Name: groper
Version: 0.4.1
Summary: Library for parsing config files and command line arguments
Project-URL: Homepage, https://github.com/ipartola/groper
Project-URL: Documentation, https://github.com/ipartola/groper
Project-URL: Repository, https://github.com/ipartola/groper.git
Project-URL: Bug Tracker, https://github.com/ipartola/groper/issues
Project-URL: Changelog, https://github.com/ipartola/groper/commits/main/
Author-email: Igor Partola <igor@igorpartola.com>
Maintainer-email: Igor Partola <igor@igorpartola.com>
License: Copyright (C) 2011-2024 Igor Partola
License-File: LICENSE.txt
Keywords: args,command line,getopt
Classifier: Development Status :: 5 - Production/Stable
Classifier: Environment :: Console
Classifier: Intended Audience :: Developers
Classifier: License :: OSI Approved :: MIT License
Classifier: Operating System :: MacOS :: MacOS X
Classifier: Operating System :: POSIX
Classifier: Programming Language :: Python
Classifier: Programming Language :: Python :: 3
Classifier: Topic :: Software Development :: Libraries
Requires-Python: >=3.1
